<launch>
    <node pkg="scr_state" exec="statemanager" >
        <param name="required_nodes" value="[autonav_display]" />
        <param name="mode" value="1" />
    </node>
    <node pkg="scr_logging" exec="logging">
        <param name="log_to_console" value="true" />
    </node>
    <node pkg="scr_configuration" exec="config">
        <param name="preset" value="simulation" />
    </node>
    <node pkg="autonav_display" exec="primary_display" output="screen">
        <param name="fullscreen" value="true" />
    </node>
    <node pkg="autonav_vision" exec="transformations.py" />
    <node pkg="autonav_vision" exec="expandify" />
    <node pkg="autonav_filters" exec="filters.py" />
    <node pkg="autonav_manual" exec="steam.py" />
    <node pkg="autonav_manual" exec="steamremote" />
    <node pkg="autonav_playback" exec="playback.py" />
</launch>